hydrocivil/__init__.py
hydrocivil/abstractions.py
hydrocivil/channels.py
hydrocivil/geomorphology.py
hydrocivil/global_vars.py
hydrocivil/graphical.py
hydrocivil/misc.py
hydrocivil/rain.py
hydrocivil/reservoirs.py
hydrocivil/unithydrographs.py
hydrocivil/watersheds.py
hydrocivil/wb_tools.py
hydrocivil/web.py
hydrocivil/resources/params.xlsx
hydrocivil/resources/synthetic_storms.csv
hydrocivil/resources/CNT2420_2/CN-T-2420_2.cpg
hydrocivil/resources/CNT2420_2/CN-T-2420_2.dbf
hydrocivil/resources/CNT2420_2/CN-T-2420_2.prj
hydrocivil/resources/CNT2420_2/CN-T-2420_2.qix
hydrocivil/resources/CNT2420_2/CN-T-2420_2.qmd
hydrocivil/resources/CNT2420_2/CN-T-2420_2.shp
hydrocivil/resources/CNT2420_2/CN-T-2420_2.shx
hydrocivil/resources/CNT2420_2/cn.tif
hydrocivil/resources/CNT2420_2/dem.tif
hydrocivil/resources/CNT2420_2/rnetwork.cpg
hydrocivil/resources/CNT2420_2/rnetwork.dbf
hydrocivil/resources/CNT2420_2/rnetwork.prj
hydrocivil/resources/CNT2420_2/rnetwork.shp
hydrocivil/resources/CNT2420_2/rnetwork.shx
hydrocivil/resources/EsteroVDM/EsteroVDM.gpkg
hydrocivil/resources/EsteroVDM/cn.tif
hydrocivil/resources/EsteroVDM/dem.tif
hydrocivil/resources/EsteroVDM/rnetwork.gpkg
hydrocivil/resources/RioGomez/Cuenca_RioGomez_v0.cpg
hydrocivil/resources/RioGomez/Cuenca_RioGomez_v0.dbf
hydrocivil/resources/RioGomez/Cuenca_RioGomez_v0.prj
hydrocivil/resources/RioGomez/Cuenca_RioGomez_v0.qmd
hydrocivil/resources/RioGomez/Cuenca_RioGomez_v0.shp
hydrocivil/resources/RioGomez/Cuenca_RioGomez_v0.shx
hydrocivil/resources/RioGomez/CurveNumber_RioGomez_v0.tif
hydrocivil/resources/RioGomez/DEM_ALOSPALSAR_RioGomez_v0.tif
hydrocivil/resources/RioGomez/rnetwork_RioGomez_v0.cpg
hydrocivil/resources/RioGomez/rnetwork_RioGomez_v0.dbf
hydrocivil/resources/RioGomez/rnetwork_RioGomez_v0.prj
hydrocivil/resources/RioGomez/rnetwork_RioGomez_v0.shp
hydrocivil/resources/RioGomez/rnetwork_RioGomez_v0.shx
hydrocivil/resources/raster/CR2MET_pr_v2.5_mean-yr_1960-2021.tif
hydrocivil-1.1.4.dist-info/licenses/LICENSE
hydrocivil-1.1.4.dist-info/METADATA
hydrocivil-1.1.4.dist-info/WHEEL
hydrocivil-1.1.4.dist-info/top_level.txt
hydrocivil-1.1.4.dist-info/RECORD
