Metadata-Version: 2.4
Name: hydrocivil
Version: 1.1.4
Summary: a package for hydrological methods in enviromental engineering
Author-email: Lucas Glasner <lgvivanco96@gmail.com>
Project-URL: Homepage, https://github.com/lucasglasner/hydrocivil
Project-URL: Issues, https://github.com/lucasglasner/hydrocivil/issues
Requires-Python: >=3.12
License-File: LICENSE
Requires-Dist: dask
Requires-Dist: gdal
Requires-Dist: geopandas
Requires-Dist: ipykernel
Requires-Dist: matplotlib
Requires-Dist: netCDF4
Requires-Dist: networkx
Requires-Dist: numba
Requires-Dist: numpy
Requires-Dist: openpyxl
Requires-Dist: pandas
Requires-Dist: rasterio
Requires-Dist: shapely
Requires-Dist: xarray
Requires-Dist: rioxarray
Requires-Dist: whitebox_workflows
Dynamic: license-file
